json_settings/__init__.py
json_settings/dictionary_setting.py
json_settings/error.py
json_settings/list_setting.py
json_settings/number_setting.py
json_settings/settings.py
json_settings/space.py
json_settings/stringset_setting.py
json_settings/terminus_setting.py
test/__init__.py
test/test_dictionary_setting.py
test/test_list_setting.py
test/test_number_setting.py
test/test_settings.py
test/test_space.py
test/test_stringset_setting.py
test/test_terminus_setting.py
json_settings-0.1.4.dist-info/LICENCE
json_settings-0.1.4.dist-info/METADATA
json_settings-0.1.4.dist-info/WHEEL
json_settings-0.1.4.dist-info/top_level.txt
json_settings-0.1.4.dist-info/RECORD
