Metadata-Version: 2.1
Name: json-settings
Version: 0.1.4
Summary: JSON Configuration File Framework
Home-page: https://github.com/riskaware-ltd/json-settings
Author: Riskaware Ltd
License: UNKNOWN
Platform: UNKNOWN
Classifier: Programming Language :: Python :: 3
Classifier: License :: OSI Approved :: MIT License
Classifier: Operating System :: OS Independent
Requires-Dist: numpy
